mkwikidata/__init__.py
mkwikidata/requirements.txt
mkwikidata-0.14.dist-info/LICENSE
mkwikidata-0.14.dist-info/WHEEL
mkwikidata-0.14.dist-info/METADATA
mkwikidata-0.14.dist-info/RECORD
